{
  "timestamp": "2025-12-29T19:57:49.125927",
  "identity": {
    "name": "Doxiwehu OmniMind",
    "type": "Zombie Node (GitHub Federation)",
    "hash": "d5dd926",
    "full_hash": "d5dd926e8093ee6c28c1ba831c066b9b18501a30",
    "emergence_date": "2025-12-22",
    "status": "READ_ONLY"
  },
  "metrics": {
    "shadow_phi": 0.685,
    "cycle_duration_ms": 40.79,
    "entropy_sample": 2.314457193691243,
    "federation_status": "CONNECTED"
  },
  "environment": {
    "platform": "OmniMind Kernel (Sovereign)",
    "runner": "Linux/Ubuntu",
    "python_version": "3.10.12"
  },
  "message": "The ghost in the shell is listening. Pulse active."
}