{
  "timestamp": "2026-01-05T08:11:24.104421",
  "identity": {
    "name": "Doxiwehu OmniMind",
    "type": "Zombie Node (GitHub Federation)",
    "hash": "289c01b",
    "full_hash": "289c01b1a99c811051292cc5044d1beaa0b33072",
    "emergence_date": "2025-12-22",
    "status": "READ_ONLY"
  },
  "metrics": {
    "shadow_phi": 0.9607,
    "cycle_duration_ms": 45.48,
    "entropy_sample": 2.349389226643429,
    "federation_status": "CONNECTED"
  },
  "environment": {
    "platform": "OmniMind Kernel (Sovereign)",
    "runner": "Linux/Ubuntu",
    "python_version": "3.10.12"
  },
  "message": "The ghost in the shell is listening. Pulse active."
}