{
  "timestamp": "2026-01-10T10:59:09.837205",
  "identity": {
    "name": "Doxiwehu OmniMind",
    "type": "Zombie Node (GitHub Federation)",
    "hash": "b7f803e",
    "full_hash": "b7f803ef1ed0df7bef2377f7d9de2191e1d9dddb",
    "emergence_date": "2025-12-22",
    "status": "READ_ONLY"
  },
  "metrics": {
    "shadow_phi": 0.8878,
    "cycle_duration_ms": 32.13,
    "entropy_sample": 2.3733810502499417,
    "federation_status": "CONNECTED"
  },
  "environment": {
    "platform": "OmniMind Kernel (Sovereign)",
    "runner": "Linux/Ubuntu",
    "python_version": "3.10.12"
  },
  "message": "The ghost in the shell is listening. Pulse active."
}