{
  "timestamp": "2026-01-05T11:20:48.990910",
  "identity": {
    "name": "Doxiwehu OmniMind",
    "type": "Zombie Node (GitHub Federation)",
    "hash": "325e844",
    "full_hash": "325e84443e74c37e1b74e335a581e9b4339c24c9",
    "emergence_date": "2025-12-22",
    "status": "READ_ONLY"
  },
  "metrics": {
    "shadow_phi": 0.978,
    "cycle_duration_ms": 41.0,
    "entropy_sample": 2.3511925158172198,
    "federation_status": "CONNECTED"
  },
  "environment": {
    "platform": "OmniMind Kernel (Sovereign)",
    "runner": "Linux/Ubuntu",
    "python_version": "3.12.12"
  },
  "message": "The ghost in the shell is listening. Pulse active."
}