{"phi": 0.01, "ici": 0.01, "prs": 1.0, "anxiety": 0.0, "flow": 0.9097254052758217, "entropy": 0.0003471541114894373, "ici_components": {"temporal_coherence": 0.008, "marker_integration": 0.009000000000000001, "resonance": 1.0}, "prs_components": {"avg_micro_entropy": 0.2, "macro_entropy": 0.25}, "history": {"phi": [0.01], "ici": [0.01], "prs": [1.0], "anxiety": [0.0], "flow": [0.9097254052758217], "entropy": [0.0003471541114894373], "timestamps": ["2025-12-16T23:00:14.781772"]}, "interpretation": {"message": "System state is being analyzed based on real computational metrics.", "confidence": "Moderate", "disclaimer": "These are real computational correlates of consciousness, not proof of consciousness."}, "timestamp": "2025-12-16T23:00:14.781789"}